[
    {
        "url": "https://www.mcbbs.net/thread-1242641-1-1.html",
        "skinName": "随手乱画Ⅵ 寒柏",
        "skinImg": "https://attachment.mcbbs.net/data/myattachment/forum/202108/10/183734twsz5znzwb5xowwx.png",
        "skinCreate": "暗夜",
        "skinTime": "2021/8/10"
    },
    {
        "url": "https://www.mcbbs.net/thread-1166621-1-1.html",
        "skinName": "随手乱画·焰",
        "skinImg": "https://attachment.mcbbs.net/data/myattachment/forum/202102/08/043155qs33joaezmyxje9e.jpg",
        "skinCreate": "暗夜",
        "skinTime": "2021/2/9"
    }
]
